prospectpredictor/PredictorByDistance.py
prospectpredictor/__init__.py
prospectpredictor/prepShapes.py
prospectpredictor/rasterTemplate.py
prospectpredictor/utils.py
prospectpredictor-0.1.1.dist-info/LICENSE
prospectpredictor-0.1.1.dist-info/METADATA
prospectpredictor-0.1.1.dist-info/WHEEL
prospectpredictor-0.1.1.dist-info/top_level.txt
prospectpredictor-0.1.1.dist-info/RECORD
