Metadata-Version: 2.1
Name: prospectpredictor
Version: 0.1.1
Summary: prospectivity prediction based on GIS shapefiles
Home-page: https://github.com/tyleracorn/prospectPredictor
Author: Tyler Acorn
Author-email: tyler.acorn@gmail.com
License: MIT
Keywords: GIS prospectivity varriogram shapefiles raster
Platform: UNKNOWN
Classifier: Development Status :: 3 - Alpha
Classifier: License :: OSI Approved :: MIT License
Classifier: Programming Language :: Python :: 3.8
Classifier: Topic :: Scientific/Engineering
Requires-Dist: geopandas
Requires-Dist: rasterio
Requires-Dist: descartes
Requires-Dist: matplotlib
